xiaogpt-3.22.dist-info/METADATA
xiaogpt-3.22.dist-info/WHEEL
xiaogpt-3.22.dist-info/entry_points.txt
xiaogpt-3.22.dist-info/licenses/LICENSE
xiaogpt/__init__.py
xiaogpt/__main__.py
xiaogpt/bot/__init__.py
xiaogpt/bot/base_bot.py
xiaogpt/bot/chatgptapi_bot.py
xiaogpt/bot/doubao_bot.py
xiaogpt/bot/gemini_bot.py
xiaogpt/bot/glm_bot.py
xiaogpt/bot/langchain_bot.py
xiaogpt/bot/llama_bot.py
xiaogpt/bot/moonshot_bot.py
xiaogpt/bot/qwen_bot.py
xiaogpt/bot/yi_bot.py
xiaogpt/cli.py
xiaogpt/config.py
xiaogpt/langchain/callbacks.py
xiaogpt/langchain/chain.py
xiaogpt/langchain/examples/email/mail_box.py
xiaogpt/langchain/examples/email/mail_summary_tools.py
xiaogpt/tts/__init__.py
xiaogpt/tts/base.py
xiaogpt/tts/file.py
xiaogpt/tts/live.py
xiaogpt/tts/mi.py
xiaogpt/utils.py
xiaogpt/xiaogpt.py
xiaogpt-3.22.dist-info/RECORD
